multisshift/__init__.py
multisshift/__main__.py
multisshift/vt.py
multisshift/Library/__init__.py
multisshift/Library/editor.py
multisshift/Library/editor_handler.py
multisshift/Library/serialschemahandler.py
multisshift/Library/serialshell.py
multisshift/Library/serialshellreader.py
multisshift/dialogs/__init__.py
multisshift/dialogs/add_session_dialog.py
multisshift/dialogs/adhoc.py
multisshift/dialogs/edit_session_dialog.py
multisshift/session_manager/__init__.py
multisshift/session_manager/session_manager.py
multisshift/terminal/__init__.py
multisshift/terminal/tabterm.py
multisshift/ui/__init__.py
multisshift/ui/ace_widget.py
multisshift/ui/context_menus.py
multisshift/ui/credentials_dialog.py
multisshift/ui/creds_dlg.py
multisshift/ui/creds_widget.py
multisshift/ui/log_viewer2.py
multisshift/ui/log_viewer_widget.py
multisshift/ui/main_window.py
multisshift/ui/serialui.py
multisshift/ui/themes.py
multisshift/ui/images/bolt.svg
multisshift/ui/images/terminal.svg
multisshift/utils/__init__.py
multisshift/utils/db.py
multisshift/utils/db_utils.py
multisshift/utils/models.py
multisshift/utils/util.py
multisshift/utils/yaml_utils.py
multisshift/web/style.css
multisshift/web/ace/editor.html
multisshift/web/ace/editor_custom.js
multisshift/web/ace/qcstuff.js
multisshift/web/ace/qtchan.js
multisshift/web/ace/css/ace.css
multisshift/web/ace/css/ambiance-1.png
multisshift/web/ace/css/ambiance-2.png
multisshift/web/ace/css/ambiance-3.png
multisshift/web/ace/css/chrome-1.png
multisshift/web/ace/css/chrome-2.png
multisshift/web/ace/css/cloud9_day-1.png
multisshift/web/ace/css/cloud9_day-2.png
multisshift/web/ace/css/cloud9_night-1.png
multisshift/web/ace/css/cloud9_night-2.png
multisshift/web/ace/css/cloud9_night_low_color-1.png
multisshift/web/ace/css/cloud9_night_low_color-2.png
multisshift/web/ace/css/clouds-1.png
multisshift/web/ace/css/clouds-2.png
multisshift/web/ace/css/clouds_midnight-1.png
multisshift/web/ace/css/clouds_midnight-2.png
multisshift-0.1.1.dist-info/LICENSE
multisshift-0.1.1.dist-info/METADATA
multisshift-0.1.1.dist-info/WHEEL
multisshift-0.1.1.dist-info/entry_points.txt
multisshift-0.1.1.dist-info/top_level.txt
multisshift-0.1.1.dist-info/RECORD
