Metadata-Version: 2.1
Name: multisshift
Version: 0.1.1
Summary: A native python SSH multi-tabbed Terminal based on PyQt6 and FastAPI
Home-page: https://github.com/scottpeterman/MultiSShift
Author: Scott Peterman
Author-email: scottpeterman@gmail.com
License: GPLv3
Classifier: Programming Language :: Python :: 3.9
Classifier: License :: OSI Approved :: GNU General Public License v3 (GPLv3)
Classifier: Operating System :: OS Independent
License-File: LICENSE
Requires-Dist: annotated-types ==0.6.0
Requires-Dist: anyio ==3.7.1
Requires-Dist: bcrypt ==4.0.1
Requires-Dist: cffi ==1.16.0
Requires-Dist: click ==8.1.7
Requires-Dist: colorama ==0.4.6
Requires-Dist: cryptography ==41.0.5
Requires-Dist: exceptiongroup ==1.1.3
Requires-Dist: fastapi ==0.104.1
Requires-Dist: greenlet ==3.0.1
Requires-Dist: h11 ==0.14.0
Requires-Dist: httptools ==0.6.1
Requires-Dist: idna ==3.4
Requires-Dist: Jinja2 ==3.1.2
Requires-Dist: MarkupSafe ==2.1.3
Requires-Dist: paramiko ==3.3.1
Requires-Dist: pycparser ==2.21
Requires-Dist: pydantic ==2.4.2
Requires-Dist: pydantic-core ==2.10.1
Requires-Dist: pyserial ==3.5
Requires-Dist: PyNaCl ==1.5.0
Requires-Dist: PyQt6 ==6.6.0
Requires-Dist: PyQt6-Qt6 ==6.6.0
Requires-Dist: PyQt6-sip ==13.6.0
Requires-Dist: PyQt6-WebEngine ==6.6.0
Requires-Dist: PyQt6-WebEngine-Qt6 ==6.6.0
Requires-Dist: python-dotenv ==1.0.0
Requires-Dist: python-multipart ==0.0.6
Requires-Dist: PyYAML ==6.0.1
Requires-Dist: sniffio ==1.3.0
Requires-Dist: SQLAlchemy ==2.0.23
Requires-Dist: starlette ==0.27.0
Requires-Dist: typing-extensions ==4.8.0
Requires-Dist: uvicorn ==0.24.0.post1
Requires-Dist: watchfiles ==0.21.0
Requires-Dist: websockets ==12.0
